Metadata-Version: 1.0
Name: pyprop
Version: 1.0
Summary: Probability Distributions
Home-page: UNKNOWN
Author: kalycodes
Author-email: kalyfacloud@gmail.com
License: UNKNOWN
Platform: UNKNOWN
